mmspy/__init__.py
mmspy/py.typed
mmspy/types.py
mmspy/api/__init__.py
mmspy/api/load.py
mmspy/api/query.py
mmspy/api/store.py
mmspy/api/processors/__init__.py
mmspy/api/processors/edp_dce.py
mmspy/api/processors/edp_scpot.py
mmspy/api/processors/feeps.py
mmspy/api/processors/fgm.py
mmspy/api/processors/fpi_dist.py
mmspy/api/processors/fpi_moms.py
mmspy/api/processors/fpi_partmoms.py
mmspy/api/processors/fsm.py
mmspy/api/processors/hpca_moments.py
mmspy/api/processors/mec.py
mmspy/api/processors/scm.py
mmspy/api/processors/utils.py
mmspy/api/processors/cdf/__init__.py
mmspy/api/processors/cdf/load.py
mmspy/api/processors/cdf/metadata.py
mmspy/api/utils/__init__.py
mmspy/api/utils/alias.py
mmspy/api/utils/file.py
mmspy/api/utils/metadata.py
mmspy/api/utils/progress_bar.py
mmspy/api/utils/remote.py
mmspy/api/utils/render_tree.py
mmspy/api/utils/request.py
mmspy/api/utils/store.py
mmspy/compute/__init__.py
mmspy/compute/curlometer.py
mmspy/compute/signal.py
mmspy/compute/transform.py
mmspy/compute/vector.py
mmspy/compute/particle/__init__.py
mmspy/compute/particle/grid.py
mmspy/compute/particle/integrate.py
mmspy/compute/particle/interpolate.py
mmspy/compute/particle/smooth.py
mmspy/compute/time_frequency/__init__.py
mmspy/compute/time_frequency/fft.py
mmspy/compute/time_frequency/stft.py
mmspy/compute/time_frequency/utils.py
mmspy/compute/utils/__init__.py
mmspy/compute/utils/index.py
mmspy/compute/utils/timing.py
mmspy/compute/utils/units.py
mmspy/configure/__init__.py
mmspy/configure/config.py
mmspy/configure/dask.py
mmspy/configure/logging.py
mmspy/configure/matplotlib.py
mmspy/configure/numba.py
mmspy/configure/paths.py
mmspy/configure/units/__init__.py
mmspy/configure/units/contexts.py
mmspy/configure/units/formatters.py
mmspy/configure/units/plasma_parameters.py
mmspy/configure/units/preprocessors.py
mmspy/configure/xarray/__init__.py
mmspy/configure/xarray/edp.py
mmspy/configure/xarray/fgm.py
mmspy/configure/xarray/fpi.py
mmspy/configure/xarray/scm.py
mmspy-0.2.9.dist-info/METADATA
mmspy-0.2.9.dist-info/WHEEL
mmspy-0.2.9.dist-info/licenses/LICENSE.md
mmspy-0.2.9.dist-info/RECORD
