Metadata-Version: 2.4
Name: mmspy
Version: 0.2.9
Summary: A Python package for querying and analysing data from the NASA Magnetospheric Multiscale (MMS) mission.
Project-URL: Repository, https://github.com/tien-vo/mmspy
Author-email: tien-vo <tvo.work@proton.me>
License: GPL-3.0
License-File: LICENSE.md
Keywords: heliophysics,magnetospheric multiscale mission,plasma,plasma physics,science,space plasma
Classifier: Development Status :: 4 - Beta
Classifier: Intended Audience :: Science/Research
Classifier: License :: OSI Approved :: GNU General Public License v3 (GPLv3)
Classifier: Natural Language :: English
Classifier: Operating System :: MacOS
Classifier: Operating System :: Microsoft :: Windows
Classifier: Operating System :: Unix
Classifier: Programming Language :: Python
Classifier: Topic :: Scientific/Engineering :: Physics
Requires-Python: >=3.11
Requires-Dist: astropy>=7.1.0
Requires-Dist: attrs<26.0.0,>=25.3.0
Requires-Dist: bigtree>=0.29.2
Requires-Dist: bokeh>=3.1.0
Requires-Dist: bs4>=0.0.2
Requires-Dist: cdflib<2.0.0,>=1.3.4
Requires-Dist: colorcet>=3.1.0
Requires-Dist: dask[distributed]<2026.0.0,>=2025.5.1
Requires-Dist: matplotlib>=3.10.3
Requires-Dist: numcodecs==0.15.1
Requires-Dist: numpy>=2.2.6
Requires-Dist: pathos>=0.3.4
Requires-Dist: pint-xarray<0.5,>=0.4
Requires-Dist: python-benedict[toml]>=0.34.1
Requires-Dist: requests>=2.32.3
Requires-Dist: rocket-fft>=0.2.5
Requires-Dist: scipy>=1.15.3
Requires-Dist: tqdm<5.0.0,>=4.67.1
Requires-Dist: xarray<2026.0.0,>=2025.4.0
Requires-Dist: zarr==2.18.5
